textual_autocomplete/__init__.py
textual_autocomplete/_autocomplete.py
textual_autocomplete/_path_autocomplete.py
textual_autocomplete/fuzzy_search.py
textual_autocomplete/py.typed
textual_autocomplete-4.0.5.dist-info/METADATA
textual_autocomplete-4.0.5.dist-info/WHEEL
textual_autocomplete-4.0.5.dist-info/licenses/LICENSE
textual_autocomplete-4.0.5.dist-info/RECORD
