Metadata-Version: 2.4
Name: textual-autocomplete
Version: 4.0.5
Summary: Easily add autocomplete dropdowns to your Textual apps.
Author-email: Darren Burns <darrenb900@gmail.com>
License-Expression: MIT
License-File: LICENSE
Classifier: Development Status :: 5 - Production/Stable
Classifier: Environment :: Console
Classifier: Intended Audience :: Developers
Classifier: License :: OSI Approved :: MIT License
Classifier: Programming Language :: Python :: 3.9
Classifier: Programming Language :: Python :: 3.10
Classifier: Programming Language :: Python :: 3.11
Classifier: Programming Language :: Python :: 3.12
Classifier: Programming Language :: Python :: 3.13
Classifier: Typing :: Typed
Requires-Python: >=3.9.0
Requires-Dist: textual>=2.0.0
Requires-Dist: typing-extensions>=4.5.0
